pigrometer/__init__.py
pigrometer/__main__.py
pigrometer/reader.py
pigrometer/server.py
pigrometer/templates/chart.html
pigrometer-0.9.dist-info/entry_points.txt
pigrometer-0.9.dist-info/METADATA
pigrometer-0.9.dist-info/WHEEL
pigrometer-0.9.dist-info/RECORD
