Metadata-Version: 2.1
Name: pigrometer
Version: 0.9
Summary: An app for capturing temperature/humidity readings on a raspberrry pi and displaying the information through a web interface
Home-page: https://github.com/BrianKmdy/PiGrometer
Author: Brian Moody
Author-email: brian.k.moody@outlook.com
Requires-Python: >=3.7,<4.0
Classifier: Programming Language :: Python :: 3
Classifier: Programming Language :: Python :: 3.7
Classifier: Programming Language :: Python :: 3.8
Classifier: Programming Language :: Python :: 3.9
Classifier: Programming Language :: Python :: 3.10
Classifier: Programming Language :: Python :: 3.11
Requires-Dist: Flask (>=2.2.2,<3.0.0)
Requires-Dist: RPi.GPIO (>=0.7.1,<0.8.0)
Requires-Dist: adafruit-circuitpython-dht (>=3.7.7,<4.0.0)
Project-URL: Repository, https://github.com/BrianKmdy/PiGrometer
